{
    "id": "506497",
    "topic": "7",
    "condition": {
        "text": "На рисунке точками изображено атмосферное давление в городе N на протяжении трёх суток с 4 по 6 апреля 2013 года. в течение суток давление измеряется 4 раза: ночью (00:00), утром (06:00), днём (12:00) и вечером (18:00). По горизонтали указывается время суток и дата, по вертикали — давление в миллиметрах ртутного столба. Для наглядности точки соединены линиями. Пользуясь рисунком, поставьте в соответствие каждому из указанных периодов времени характеристику давления в городе N в течение этого периода.ПЕРИОДЫ ВРЕМЕНИА) ночь 4 апреля (с 0 до 6 часов)Б) день 5 апреля (с 12 до 18 часов)В) ночь 6 апреля (с 0 до 6 часов)Г) утро 6 апреля (с 6 до 12 часов)ХАРАКТЕРИСТИКИ ДАВЛЕНИЯ1) наибольший рост давления2) давление достигло 758 мм рт. ст.3) давление не менялось4) наименьший рост давленияЗапишите в ответ цифры, расположив их в порядке, соответствующем буквам: АБВГ",
        "images": [
            "https://mathb-ege.sdamgia.ru/get_file?id=105471"
        ]
    },
    "answer": "2413",
    "analogs": [
        "506497",
        "506517",
        "506546",
        "509619",
        "...",
        "506517",
        "506546",
        "509619",
        "511987"
    ],
    "url": "https://mathb-ege.sdamgia.ru/problem?id=506497"
}