{
    "gia_type": "ege",
    "subject": "math",
    "id": 521071,
    "condition": {
        "text": "Дано уравнение а)  Решите уравнение.б)  Укажите корни этого уравнения, принадлежащие отрезку",
        "html": "<div align=\"justify\" width=\"100%\" id=\"body630163\" class=\"pbody\"><p class=\"left_margin\">Дано&nbsp;урав­не­ние <img src=\"https://ege.sdamgia.ru/formula/svg/dd/dd0419d467fdf056a51ff40cccf7b678.svg\" class=\"tex\" style=\"vertical-align:-1.8pt\" alt=\"4 ко­си­нус в сте­пе­ни 4 x минус 5 ко­си­нус 2x минус 1 = 0.\"></p><p class=\"left_margin\">а)  Ре­ши­те урав­не­ние.</p><p class=\"left_margin\">б)  Ука­жи­те&nbsp;корни этого урав­не­ния, при­над­ле­жа­щие&nbsp;от­рез­ку<img src=\"https://ege.sdamgia.ru/formula/svg/88/88e601d8b640d2f1d6fc6f6dd6112a1d.svg\" class=\"tex\" style=\"vertical-align:-3.6pt\" alt=\" левая квад­рат­ная скоб­ка арк­ко­си­нус 0; арк­ко­си­нус левая круг­лая скоб­ка минус 1 пра­вая круг­лая скоб­ка пра­вая квад­рат­ная скоб­ка .\"></p></div>",
        "image_urls": [
            "https://ege.sdamgia.ru/formula/svg/dd/dd0419d467fdf056a51ff40cccf7b678.svg",
            "https://ege.sdamgia.ru/formula/svg/88/88e601d8b640d2f1d6fc6f6dd6112a1d.svg"
        ]
    },
    "solution": {
        "text": "Решение. Применим формулу косинуса двойного угла Обозначив   получим б)  На промежутке  лежит корень   Ответ: а)     б) ",
        "html": "<div align=\"justify\" width=\"100%\" id=\"sol521071\" class=\"solution\" style=\"clear:both;\" class=\"pbody\"><p class=\"left_margin\"></p><b>Ре­ше­ние<!--rule_info-->. </b><p class=\"left_margin\">При­ме­ним фор­му­лу ко­си­ну­са двой­но­го угла </p><p class=\"left_margin\"></p><center><p><img src=\"https://ege.sdamgia.ru/formula/svg/f2/f20127b45677d5d2329ea913125d7f6a.svg\" class=\"tex\" style=\"vertical-align:-3.6pt\" alt=\"4 ко­си­нус в сте­пе­ни 4 x минус 5 ко­си­нус 2x минус 1 = 0 рав­но­силь­но 4 ко­си­нус в сте­пе­ни 4 x минус 5 левая круг­лая скоб­ка 2 ко­си­нус в квад­ра­те x минус 1 пра­вая круг­лая скоб­ка минус 1=0.\"></p><p class=\"left_margin\"></p></center><p class=\"left_margin\">Обо­зна­чив <img src=\"https://ege.sdamgia.ru/formula/svg/26/26babfef1e7e80e0c2248d7e8827d5c3.svg\" class=\"tex\" style=\"vertical-align:-3.6pt\" alt=\" t= ко­си­нус в квад­ра­те x, t при­над­ле­жит левая квад­рат­ная скоб­ка 0; 1 пра­вая квад­рат­ная скоб­ка \">  по­лу­чим </p><p class=\"left_margin\"></p><center><p><img src=\"https://ege.sdamgia.ru/formula/svg/5c/5ceffdbb6a177649eea40810abcc3800.svg\" class=\"tex\" style=\"vertical-align:-18.0pt\" alt=\" 4t в квад­ра­те минус 10t плюс 4=0 рав­но­силь­но со­во­куп­ность вы­ра­же­ний t=2, t= дробь: чис­ли­тель: 1, зна­ме­на­тель: 2 конец дроби конец со­во­куп­но­сти . рав­но­силь­но ко­си­нус x=\\pm дробь: чис­ли­тель: ко­рень из: на­ча­ло ар­гу­мен­та: 2 конец ар­гу­мен­та , зна­ме­на­тель: 2 конец дроби рав­но­силь­но x= дробь: чис­ли­тель: Пи , зна­ме­на­тель: 4 конец дроби плюс дробь: чис­ли­тель: Пи k, зна­ме­на­тель: 2 конец дроби , k при­над­ле­жит Z . \"></p><p class=\"left_margin\"></p></center><p class=\"left_margin\">б)  На про­ме­жут­ке <img src=\"https://ege.sdamgia.ru/formula/svg/d7/d72afb121c8caca334aa5500c379b7a4.svg\" class=\"tex\" style=\"vertical-align:-8.3pt\" alt=\" левая квад­рат­ная скоб­ка дробь: чис­ли­тель: Пи , зна­ме­на­тель: 2 конец дроби ; Пи пра­вая квад­рат­ная скоб­ка \"> лежит ко­рень <img src=\"https://ege.sdamgia.ru/formula/svg/af/afe45ace865fe02991e240942a13efce.svg\" class=\"tex\" style=\"vertical-align:-8.4pt\" alt=\" дробь: чис­ли­тель: 3 Пи , зна­ме­на­тель: 4 конец дроби . \"> </p><p>&nbsp;</p><p><span style=\"letter-spacing: 2px;\">Ответ:</span> а) <img src=\"https://ege.sdamgia.ru/formula/svg/93/93eda5b22935893d38ac53732efbd681.svg\" class=\"tex\" style=\"vertical-align:-8.4pt\" alt=\" x= дробь: чис­ли­тель: Пи , зна­ме­на­тель: 4 конец дроби плюс дробь: чис­ли­тель: Пи k, зна­ме­на­тель: 2 конец дроби , \">  <img src=\"https://ege.sdamgia.ru/formula/svg/bc/bcdc34a37df3a70a6b6ab786fa6c77d4.svg\" class=\"tex\" style=\"vertical-align:-2.3pt\" alt=\" k при­над­ле­жит Z ;\">  б) <img src=\"https://ege.sdamgia.ru/formula/svg/15/15774567d24166b3217dc36e1639e72b.svg\" class=\"tex\" style=\"vertical-align:-8.4pt\" alt=\" дробь: чис­ли­тель: 3 Пи , зна­ме­на­тель: 4 конец дроби . \"></p></div>",
        "image_urls": [
            "https://ege.sdamgia.ru/formula/svg/f2/f20127b45677d5d2329ea913125d7f6a.svg",
            "https://ege.sdamgia.ru/formula/svg/26/26babfef1e7e80e0c2248d7e8827d5c3.svg",
            "https://ege.sdamgia.ru/formula/svg/5c/5ceffdbb6a177649eea40810abcc3800.svg",
            "https://ege.sdamgia.ru/formula/svg/d7/d72afb121c8caca334aa5500c379b7a4.svg",
            "https://ege.sdamgia.ru/formula/svg/af/afe45ace865fe02991e240942a13efce.svg",
            "https://ege.sdamgia.ru/formula/svg/93/93eda5b22935893d38ac53732efbd681.svg",
            "https://ege.sdamgia.ru/formula/svg/bc/bcdc34a37df3a70a6b6ab786fa6c77d4.svg",
            "https://ege.sdamgia.ru/formula/svg/15/15774567d24166b3217dc36e1639e72b.svg"
        ]
    },
    "answer": "а)     б)",
    "topic_id": null,
    "analog_ids": []
}