{
    "gia_type": "ege",
    "subject": "math",
    "id": 509479,
    "condition": {
        "text": "Сторона основания и высота правильной шестиугольной пирамиды пирамиды равны a.‍ Найдите радиус сферы, описанной около пирамиды.",
        "html": "<div align=\"justify\" width=\"100%\" id=\"body633051\" class=\"pbody\"><p class=\"left_margin\">Сто­ро­на ос­но­ва­ния и вы­со­та пра­виль­ной ше­сти­уголь­ной пи­ра­ми­ды пи­ра­ми­ды равны <i>a</i>.‍ Най­ди­те ра­ди­ус сферы, опи­сан­ной около пи­ра­ми­ды.</p></div>",
        "image_urls": []
    },
    "solution": {
        "text": "Решение. Пусть ABCDEFP  — ‍ данная правильная шестиугольная пирамида с вершиной P,‍ AB  =  BC  =  CD  =  DE  =  EF  =  AF  =  a,‍ M  — ‍ центр правильного шестиугольника ABCDEF.‍ Поскольку пирамида правильная, PM  — ‍ её высота, а так как по условию PM = a,‍ то точка M‍ равноудалена от всех вершин пирамиды ABCDEFP.‍ Значит, M  — ‍ центр сферы, описанной около пирамиды ABCDEFP.‍ Следовательно, радиус этой сферы равен a.‍ Ответ: a.",
        "html": "<div align=\"justify\" width=\"100%\" id=\"sol509479\" class=\"solution\" style=\"clear:both;\" class=\"pbody\"><p class=\"left_margin\"></p><b>Ре­ше­ние<!--rule_info-->. </b><p class=\"left_margin\"><img src=\"/get_file?id=26208\" style=\"float:right;margin:10px\"></p><p class=\"left_margin\">Пусть <i>ABCDEFP</i>  — ‍ дан­ная пра­виль­ная ше­сти­уголь­ная пи­ра­ми­да с вер­ши­ной <i>P,‍ AB  =  BC  =  CD  =  DE  =  EF  =  AF  =  a,‍ M</i>  — ‍ центр пра­виль­но­го ше­сти­уголь­ни­ка <i>ABCDEF</i>.‍ По­сколь­ку пи­ра­ми­да пра­виль­ная, <i>PM</i>  — ‍ её вы­со­та, а так как по усло­вию <i>PM = a</i>,‍ то точка <i>M‍</i> рав­но­уда­ле­на от всех вер­шин пи­ра­ми­ды <i>ABCDEFP</i>.‍ Зна­чит, <i>M</i>  — ‍ центр сферы, опи­сан­ной около пи­ра­ми­ды <i>ABCDEFP</i>.‍ Сле­до­ва­тель­но, ра­ди­ус этой сферы равен <i>a</i>.‍</p><p>&nbsp;</p><p><span style=\"letter-spacing: 2px;\">Ответ:</span> <i>a</i>.</p></div>",
        "image_urls": [
            "/get_file?id=26208"
        ]
    },
    "answer": "a.",
    "topic_id": null,
    "analog_ids": []
}