{
    "id": 69527,
    "topic": "7",
    "condition": {
        "text": "Найдите значение выражения",
        "images": [
            "https://ege.sdamgia.ru/formula/svg/92/92430ee409cde4e7892d98afa9b79a25.svg"
        ]
    },
    "solution": {
        "text": "Ре­ше­ние.Это за­да­ние ещё не ре­ше­но, при­во­дим ре­ше­ние про­то­ти­па.Най­ди­те зна­че­ние вы­ра­же­ния Вы­пол­ним пре­об­ра­зо­ва­ния:   Ответ: 3.",
        "images": [
            "https://ege.sdamgia.ru/formula/svg/9c/9cc7c351333208d941ac8205de418292.svg",
            "https://ege.sdamgia.ru/formula/svg/58/5860b2a4e25583055df0dded40f74523.svg"
        ]
    },
    "answer": "12",
    "analogs": [
        "26885",
        "69543",
        "4345",
        "4347",
        "...",
        "69543",
        "4345",
        "4347",
        "4349",
        "69487",
        "69489",
        "69491",
        "69493",
        "69495",
        "69497",
        "69499",
        "69501",
        "69503",
        "69505",
        "69507",
        "69509",
        "69511",
        "69513",
        "69515",
        "69517",
        "69519",
        "69521",
        "69523",
        "69525",
        "69529",
        "69531",
        "69533",
        "69535",
        "69537",
        "69539",
        "69541"
    ],
    "url": "https://math-ege.sdamgia.ru/problem?id=69527"
}