{
    "id": "27236",
    "topic": "Д15",
    "condition": {
        "text": "В треугольнике ABC угол C равен 90°, Найдите",
        "images": [
            "https://ege.sdamgia.ru/formula/svg/22/22537bb22e4a90b08f4ed10bd12e7744.svg",
            "https://ege.sdamgia.ru/formula/svg/a6/a6b34978fd88f3c7a15bccdd531d7a49.svg",
            "https://ege.sdamgia.ru/formula/svg/55/55c9ee3beff9b131586901889ba3714f.svg",
            "https://mathb-ege.sdamgia.ru/get_file?id=7669"
        ]
    },
    "answer": "4",
    "analogs": [
        "27236",
        "29437",
        "29341",
        "29343",
        "...",
        "29437",
        "29341",
        "29343",
        "29345",
        "29347",
        "29349",
        "29351",
        "29353",
        "29355",
        "29357",
        "29359",
        "29361",
        "29363",
        "29365",
        "29367",
        "29369",
        "29371",
        "29373",
        "29375",
        "29377",
        "29379",
        "29381",
        "29383",
        "29385",
        "29387",
        "29389",
        "29391",
        "29393",
        "29395",
        "29397",
        "29399",
        "29401",
        "29403",
        "29405",
        "29407",
        "29409",
        "29411",
        "29413",
        "29415",
        "29417",
        "29419",
        "29421",
        "29423",
        "29425",
        "29427",
        "29429",
        "29431",
        "29433",
        "29435"
    ],
    "url": "https://mathb-ege.sdamgia.ru/problem?id=27236"
}