{
    "id": 530664,
    "topic": "6",
    "condition": {
        "text": "Найдите корень уравнения",
        "images": [
            "https://ege.sdamgia.ru/formula/svg/48/48ae07f45e951d2d1cf15e213a6a32bc.svg"
        ]
    },
    "solution": {
        "text": "Ре­ше­ние. Пе­рей­дем к од­но­му ос­но­ва­нию сте­пе­ни: Ответ: 13,5",
        "images": [
            "https://ege.sdamgia.ru/formula/svg/19/19257dc9447bdf4ecb29a766b74d8581.svg"
        ]
    },
    "answer": "13,5",
    "analogs": [
        "26654",
        "2899",
        "2943",
        "2947",
        "...",
        "2899",
        "2943",
        "2947",
        "530684",
        "654828",
        "654916",
        "2901",
        "2903",
        "2905",
        "2907",
        "2909",
        "2911",
        "2913",
        "2915",
        "2917",
        "2919",
        "2921",
        "2923",
        "2925",
        "2927",
        "2929",
        "2931",
        "2933",
        "2935",
        "2937",
        "2939",
        "2941",
        "2945"
    ],
    "url": "https://math-ege.sdamgia.ru/problem?id=530664"
}