{
    "gia_type": "ege",
    "subject": "math",
    "id": 484548,
    "condition": {
        "text": "Решите уравнение ",
        "html": "<div align=\"justify\" width=\"100%\" id=\"body592440\" class=\"pbody\"><p class=\"left_margin\">Ре­ши­те урав­не­ние <img src=\"https://ege.sdamgia.ru/formula/svg/bf/bfa3a6b88d6db8d49f29bbb84cf90949.svg\" class=\"tex\" style=\"vertical-align:-11.0pt\" alt=\" дробь: чис­ли­тель: 2 синус в квад­ра­те x плюс 2 синус x ко­си­нус 2x минус 1, зна­ме­на­тель: ко­рень из: на­ча­ло ар­гу­мен­та: ко­си­нус x конец ар­гу­мен­та конец дроби =0. \"></p></div>",
        "image_urls": [
            "https://ege.sdamgia.ru/formula/svg/bf/bfa3a6b88d6db8d49f29bbb84cf90949.svg"
        ]
    },
    "solution": {
        "text": "Решение. Решим уравнение   Из найденный решений условию  удовлетворяет только   и Ответ: ",
        "html": "<div align=\"justify\" width=\"100%\" id=\"sol484548\" class=\"solution\" style=\"clear:both;\" class=\"pbody\"><p class=\"left_margin\"></p><b>Ре­ше­ние<!--rule_info-->. </b><p class=\"left_margin\"></p><center><p class=\"left_margin\"><img src=\"https://ege.sdamgia.ru/formula/svg/08/081b68d9e33291f1836ed6cb0ceb98ec.svg\" class=\"tex\" style=\"vertical-align:-14.4pt\" alt=\" дробь: чис­ли­тель: 2 синус в квад­ра­те x плюс 2 синус x ко­си­нус 2x минус 1, зна­ме­на­тель: ко­рень из: на­ча­ло ар­гу­мен­та: ко­си­нус x конец ар­гу­мен­та конец дроби =0 рав­но­силь­но си­сте­ма вы­ра­же­ний 2 синус x ко­си­нус 2x минус ко­си­нус 2x=0, ко­си­нус x боль­ше 0. конец си­сте­мы . \"></p><p class=\"left_margin\"></p></center><p class=\"left_margin\">Решим урав­не­ние <img src=\"https://ege.sdamgia.ru/formula/svg/ee/ee42751c0d41b9621237fabe1374f7a8.svg\" class=\"tex\" style=\"vertical-align:-1.8pt\" alt=\"2 синус x ко­си­нус 2x минус ко­си­нус 2x=0:\"></p><p class=\"left_margin\"></p><center><p><img src=\"/get_file?id=40498\" style=\"float:right;margin:10px;max-width:100%\"></p><p><span data-width=\"640\" data-formulahash=\"fe49d92fc81c6de2cac2c227317a978e\" class=\"tex-span\" style=\"\"><img src=\"https://ege.sdamgia.ru/formula/svg/fe/fe49d92fc81c6de2cac2c227317a978e.svg\" class=\"tex\" style=\"vertical-align:-34.6pt\" alt=\"2 синус x ко­си­нус 2x минус ко­си­нус 2x=0 рав­но­силь­но ко­си­нус 2x левая круг­лая скоб­ка 2 синус x минус 1 пра­вая круг­лая скоб­ка =0 рав­но­силь­но со­во­куп­ность вы­ра­же­ний ко­си­нус 2x=0, синус x= дробь: чис­ли­тель: 1, зна­ме­на­тель: 2 конец дроби , конец со­во­куп­но­сти рав­но­силь­но со­во­куп­ность вы­ра­же­ний x= дробь: чис­ли­тель: Пи , зна­ме­на­тель: 4 конец дроби плюс дробь: чис­ли­тель: Пи k, зна­ме­на­тель: 2 конец дроби ,x= дробь: чис­ли­тель: Пи , зна­ме­на­тель: 6 конец дроби плюс 2 Пи k, x= дробь: чис­ли­тель: 5 Пи , зна­ме­на­тель: 6 конец дроби плюс 2 Пи k,k при­над­ле­жит Z . конец со­во­куп­но­сти . \"></span><span data-width=\"590\" data-formulahash=\"fe49d92fc81c6de2cac2c227317a978e\" class=\"tex-span\" style=\"display:none\"><img src=\"https://ege.sdamgia.ru/formula/svg/74/7449cb9c411bdda24a67e0e324472984.svg\" class=\"tex\" style=\"vertical-align:-3.6pt\" alt=\"2 синус x ко­си­нус 2x минус ко­си­нус 2x=0 рав­но­силь­но ко­си­нус 2x левая круг­лая скоб­ка 2 синус x минус 1 пра­вая круг­лая скоб­ка =0 рав­но­силь­но \"><br><img src=\"https://ege.sdamgia.ru/formula/svg/e2/e228d701efa379886807f085aed5e788.svg\" class=\"tex\" style=\"vertical-align:-34.6pt\" alt=\" рав­но­силь­но со­во­куп­ность вы­ра­же­ний ко­си­нус 2x=0, синус x= дробь: чис­ли­тель: 1, зна­ме­на­тель: 2 конец дроби , конец со­во­куп­но­сти рав­но­силь­но со­во­куп­ность вы­ра­же­ний x= дробь: чис­ли­тель: Пи , зна­ме­на­тель: 4 конец дроби плюс дробь: чис­ли­тель: Пи k, зна­ме­на­тель: 2 конец дроби ,x= дробь: чис­ли­тель: Пи , зна­ме­на­тель: 6 конец дроби плюс 2 Пи k, x= дробь: чис­ли­тель: 5 Пи , зна­ме­на­тель: 6 конец дроби плюс 2 Пи k,k при­над­ле­жит Z . конец со­во­куп­но­сти . \"></span></p><p class=\"left_margin\"></p></center><p>&nbsp;</p><p>&nbsp;</p><p class=\"left_margin\">Из най­ден­ный ре­ше­ний усло­вию <img src=\"https://ege.sdamgia.ru/formula/svg/e4/e40ed7d9e11e382d301d2e349a946d1a.svg\" class=\"tex\" style=\"vertical-align:-1.8pt\" alt=\" ко­си­нус x боль­ше 0\"> удо­вле­тво­ря­ет толь­ко <img src=\"https://ege.sdamgia.ru/formula/svg/0d/0d8e976a7a9a47bfcb295888f6be56a4.svg\" class=\"tex\" style=\"vertical-align:-8.4pt\" alt=\"x= дробь: чис­ли­тель: Пи , зна­ме­на­тель: 4 конец дроби плюс 2 Пи k, \"> <img src=\"https://ege.sdamgia.ru/formula/svg/47/472509ff0d806b042adab59b5eeb9025.svg\" class=\"tex\" style=\"vertical-align:-8.4pt\" alt=\"x= минус дробь: чис­ли­тель: Пи , зна­ме­на­тель: 4 конец дроби плюс 2 Пи k \"> и <img src=\"https://ege.sdamgia.ru/formula/svg/4d/4d4576a7d4b17d6a8a7683b71e2cce8d.svg\" class=\"tex\" style=\"vertical-align:-8.5pt\" alt=\"x= дробь: чис­ли­тель: Пи , зна­ме­на­тель: 6 конец дроби плюс 2 Пи k,k при­над­ле­жит Z . \"></p><p class=\"left_margin\">Ответ: <img src=\"https://ege.sdamgia.ru/formula/svg/d1/d158ffc4fcf871a4afae8f889c441b97.svg\" class=\"tex\" style=\"vertical-align:-8.4pt\" alt=\" левая фи­гур­ная скоб­ка минус дробь: чис­ли­тель: Пи , зна­ме­на­тель: 4 конец дроби плюс 2 Пи k, дробь: чис­ли­тель: Пи , зна­ме­на­тель: 4 конец дроби плюс 2 Пи k, дробь: чис­ли­тель: Пи , зна­ме­на­тель: 6 конец дроби плюс 2 Пи k: k при­над­ле­жит Z пра­вая фи­гур­ная скоб­ка . \"></p></div>",
        "image_urls": [
            "https://ege.sdamgia.ru/formula/svg/08/081b68d9e33291f1836ed6cb0ceb98ec.svg",
            "https://ege.sdamgia.ru/formula/svg/ee/ee42751c0d41b9621237fabe1374f7a8.svg",
            "https://ege.sdamgia.ru/formula/svg/fe/fe49d92fc81c6de2cac2c227317a978e.svg",
            "https://ege.sdamgia.ru/formula/svg/74/7449cb9c411bdda24a67e0e324472984.svg",
            "https://ege.sdamgia.ru/formula/svg/e2/e228d701efa379886807f085aed5e788.svg",
            "https://ege.sdamgia.ru/formula/svg/e4/e40ed7d9e11e382d301d2e349a946d1a.svg",
            "https://ege.sdamgia.ru/formula/svg/0d/0d8e976a7a9a47bfcb295888f6be56a4.svg",
            "https://ege.sdamgia.ru/formula/svg/47/472509ff0d806b042adab59b5eeb9025.svg",
            "https://ege.sdamgia.ru/formula/svg/4d/4d4576a7d4b17d6a8a7683b71e2cce8d.svg",
            "https://ege.sdamgia.ru/formula/svg/d1/d158ffc4fcf871a4afae8f889c441b97.svg",
            "/get_file?id=40498"
        ]
    },
    "answer": "",
    "topic_id": null,
    "analog_ids": [
        484548,
        484549,
        511288
    ]
}