{
    "gia_type": "ege",
    "subject": "math",
    "id": 503131,
    "condition": {
        "text": "Поезд отправился из Санкт-Петербурга в 23 часа 50 минут и прибыл в Москву в 7 часов 50 минут следующих суток. Сколько часов поезд находился в пути?",
        "html": "<div align=\"justify\" width=\"100%\" id=\"body639911\" class=\"pbody\"><p class=\"left_margin\">Поезд от­пра­вил­ся из Санкт-Пе­тер­бур­га в 23 часа 50 минут и при­был в Моск­ву в 7 часов 50 минут сле­ду­ю­щих суток. Сколь­ко часов поезд на­хо­дил­ся в пути?</p></div>",
        "image_urls": []
    },
    "solution": {
        "text": "Решение. Поезд находился в пути 10 минут до полуночи и еще 7 часов 50 минут после полуночи. Всего 8 часов. Ответ: 8.",
        "html": "<div align=\"justify\" width=\"100%\" id=\"sol503131\" class=\"solution\" style=\"clear:both;\" class=\"pbody\"><p class=\"left_margin\"></p><b>Ре­ше­ние<!--rule_info-->. </b><p class=\"left_margin\">Поезд на­хо­дил­ся в пути 10 минут до по­лу­но­чи и еще 7 часов 50 минут после по­лу­но­чи. Всего 8 часов.</p><p>&nbsp;</p><p><span style=\"letter-spacing: 2px;\">Ответ:</span> 8.</p></div>",
        "image_urls": []
    },
    "answer": "8",
    "topic_id": null,
    "analog_ids": []
}