{
    "gia_type": "ege",
    "subject": "math",
    "id": 562077,
    "condition": {
        "text": "В равнобедренном треугольнике ABC (AB = BC) проведены высоты AK, BM, CP.а)  Докажите, что треугольник KMP  — равнобедренный.б)  Найдите площадь треугольника ABC, если известно, что площадь треугольника KMP равна 12, а косинус угла ABC равен 0,6.",
        "html": "<div align=\"justify\" width=\"100%\" id=\"body458081\" class=\"pbody\"><p class=\"left_margin\">В рав­но­бед­рен­ном тре­уголь­ни­ке <i>ABC</i> (<i>AB = BC</i>) про­ве­де­ны вы­со­ты <i>AK, BM, CP.</i></p><p class=\"left_margin\">а)  До­ка­жи­те, что тре­уголь­ник <i>KMP</i>  — рав­но­бед­рен­ный.</p><p class=\"left_margin\">б)  Най­ди­те пло­щадь тре­уголь­ни­ка <i>ABC</i>, если из­вест­но, что пло­щадь тре­уголь­ни­ка <i>KMP</i> равна 12, а ко­си­нус угла <i>ABC</i> равен 0,6.</p></div>",
        "image_urls": []
    },
    "solution": {
        "text": "Решение. а)  Рассмотрим треугольники APC и CKA: углы PAC и  KCA равны как углы при основании равнобедренного треугольника, углы APC и  CKA равны (прямые углы), сторона AC  — общая. Значит, треугольники APC и CKA  равны по гипотенузе и острому углу. Точка M является серединой AC. Отрезки MP и MK равны, как соответствующие элементы (медианы проведенные к гипотенузам) равных треугольников. Значит, треугольник KMP  — равнобедренный. б)  Из равенства треугольников APC и CKA следует равенство отрезков AP и CK, а значит и равенство отрезков PB и KB. Тогда треугольники PBK и ABC подобны. Коэффициент подобия равен  Из подобия треугольников получаем   Выразим площадь треугольника KMP:Таким образом, площадь треугольника ABC:  Ответ: б) 50.",
        "html": "<div align=\"justify\" width=\"100%\" id=\"sol562077\" class=\"solution\" style=\"clear:both;\" class=\"pbody\"><p class=\"left_margin\"></p><b>Ре­ше­ние<!--rule_info-->. </b><p class=\"left_margin\"><img src=\"/get_file?id=85747\" style=\"float:right;margin:10px;max-width:100%\">а)  Рас­смот­рим тре­уголь­ни­ки <i>APC</i> и <i>CKA</i>: углы <i>PAC</i> и  <i>KCA</i> равны как углы при ос­но­ва­нии рав­но­бед­рен­но­го тре­уголь­ни­ка, углы <i>APC</i> и  <i>CKA</i> равны (пря­мые углы), сто­ро­на <i>AC</i>  — общая. Зна­чит, тре­уголь­ни­ки <i>APC</i> и <i>CKA</i>  равны по ги­по­те­ну­зе и остро­му углу. Точка <i>M</i> яв­ля­ет­ся се­ре­ди­ной <i>AC</i>. От­рез­ки <i>MP</i> и <i>MK</i> равны, как со­от­вет­ству­ю­щие эле­мен­ты (ме­ди­а­ны про­ве­ден­ные к ги­по­те­ну­зам) рав­ных тре­уголь­ни­ков. Зна­чит, тре­уголь­ник <i>KMP</i>  — рав­но­бед­рен­ный.</p><p>&nbsp;</p><p class=\"left_margin\">б)  Из ра­вен­ства тре­уголь­ни­ков <i>APC</i> и <i>CKA</i> сле­ду­ет ра­вен­ство от­рез­ков <i>AP</i> и <i>CK</i>, а зна­чит и ра­вен­ство от­рез­ков <i>PB</i> и <i>KB</i>. Тогда тре­уголь­ни­ки <i>PBK</i> и <i>ABC</i> по­доб­ны. Ко­эф­фи­ци­ент по­до­бия равен <img src=\"https://ege.sdamgia.ru/formula/svg/5d/5dce440783d9129461906dcb191af9ce.svg\" class=\"tex\" style=\"vertical-align:-8.4pt\" alt=\"k= дробь: чис­ли­тель: PB, зна­ме­на­тель: AB конец дроби = дробь: чис­ли­тель: BK, зна­ме­на­тель: AB конец дроби = ко­си­нус ABC = 0,6. \"> Из по­до­бия тре­уголь­ни­ков по­лу­ча­ем <img src=\"https://ege.sdamgia.ru/formula/svg/48/48424f7be178bf3f74f6b7b0a69f1262.svg\" class=\"tex\" style=\"vertical-align:-3.0pt\" alt=\"PK=0,6AC,\"> <img src=\"https://ege.sdamgia.ru/formula/svg/c2/c25bdd27648ffa8b494caadd188e8d0c.svg\" class=\"tex\" style=\"vertical-align:-3.0pt\" alt=\"HM=0,4BM.\"> Вы­ра­зим пло­щадь тре­уголь­ни­ка <i>KMP</i>:</p><p class=\"left_margin\"></p><center><p><img src=\"https://ege.sdamgia.ru/formula/svg/90/90f7cadf1444d8daf309b6841312fe48.svg\" class=\"tex\" style=\"vertical-align:-8.4pt\" alt=\" S_KMP= дробь: чис­ли­тель: 1, зна­ме­на­тель: 2 конец дроби PK умно­жить на HM= дробь: чис­ли­тель: 1, зна­ме­на­тель: 2 конец дроби умно­жить на 0,6AC умно­жить на 0,4BM=S_ABC умно­жить на 0,6 умно­жить на 0,4\"></p><p class=\"left_margin\"></p></center><p class=\"left_margin\">Таким об­ра­зом, пло­щадь тре­уголь­ни­ка <i>ABC</i>:</p><p class=\"left_margin\"></p><center><p><img src=\"https://ege.sdamgia.ru/formula/svg/d5/d50c2191859bb9bf4f86a5cef369ee31.svg\" class=\"tex\" style=\"vertical-align:-10.5pt\" alt=\" S_ABC= дробь: чис­ли­тель: S_PKM, зна­ме­на­тель: 0,6 умно­жить на 0,4 конец дроби = дробь: чис­ли­тель: 12, зна­ме­на­тель: 0,6 умно­жить на 0,4 конец дроби =50 \"></p><p class=\"left_margin\"></p></center><p> </p><p>&nbsp;</p><p><span style=\"letter-spacing: 2px;\">Ответ:</span> б) 50.</p></div>",
        "image_urls": [
            "https://ege.sdamgia.ru/formula/svg/5d/5dce440783d9129461906dcb191af9ce.svg",
            "https://ege.sdamgia.ru/formula/svg/48/48424f7be178bf3f74f6b7b0a69f1262.svg",
            "https://ege.sdamgia.ru/formula/svg/c2/c25bdd27648ffa8b494caadd188e8d0c.svg",
            "https://ege.sdamgia.ru/formula/svg/90/90f7cadf1444d8daf309b6841312fe48.svg",
            "https://ege.sdamgia.ru/formula/svg/d5/d50c2191859bb9bf4f86a5cef369ee31.svg",
            "/get_file?id=85747"
        ]
    },
    "answer": "б) 50.",
    "topic_id": null,
    "analog_ids": [
        562077,
        508667
    ]
}